part2/part2b.v
module part2b (
    input clk,
    input [7:0] I,
    input [2:0] O1Sel,
    input [2:0] O2Sel,
    input [1:0] FunSel,
    input [3:0] RSel,
    input [3:0] TSel,
    output reg [7:0] O1,
    O2
);

    reg [7:0] R1;
    reg [7:0] R2;
    reg [7:0] R3;
    reg [7:0] R4;
    
    reg [7:0] T1;
    reg [7:0] T2;
    reg [7:0] T3;
    reg [7:0] T4;
 
    always @ (posedge clk) begin

        if(FunSel == 2'b00) begin
            if(RSel[0] == 1) 
                 R4 <= 8'b00000000;
            if(RSel[1] == 1) 
                 R3 <= 8'b00000000;
            if(RSel[2] == 1) 
                 R2 <= 8'b00000000;
            if(RSel[3] == 1) 
                 R1 <= 8'b00000000;
            if(TSel[0] == 1) 
                 T4 <= 8'b00000000;
            if(TSel[1] == 1) 
                 T3 <= 8'b00000000;
            if(TSel[2] == 1) 
                 T2 <= 8'b00000000;
            if(TSel[3] == 1) 
                 T1 <= 8'b00000000;
        end
        else if(FunSel == 2'b01) begin
            if(RSel[0])  R4 <= I;
            if(RSel[1])  R3 <= I;
            if(RSel[2])  R2 <= I;
            if(RSel[3])  R1 <= I;
            if(TSel[0])  T4 <= I;
            if(TSel[1])  T3 <= I;
            if(TSel[2])  T2 <= I;
            if(TSel[3])  T1 <= I;
        end
        else if(FunSel == 2'b10) begin
            if(RSel[0])  R4 <= R4 - 1;
            if(RSel[1])  R3 <= R3 - 1;
            if(RSel[2])  R2 <= R2 - 1;
            if(RSel[3])  R1 <= R1 - 1;
            if(TSel[0])  T4 <= T4 - 1;
            if(TSel[1])  T3 <= T3 - 1;
            if(TSel[2])  T2 <= T2 - 1;
            if(TSel[3])  T1 <= T1 - 1;
        end
        else if(FunSel == 2'b11) begin
            if(RSel[0])  R4 <= R4 + 1;
            if(RSel[1])  R3 <= R3 + 1;
            if(RSel[2])  R2 <= R2 + 1;
            if(RSel[3])  R1 <= R1 + 1;
            if(TSel[0])  T4 <= T4 + 1;
            if(TSel[1])  T3 <= T3 + 1;
            if(TSel[2])  T2 <= T2 + 1;
            if(TSel[3])  T1 <= T1 + 1;
        end
                
        if( O1Sel == 3'b000)  O1 <= T1;
        else if( O1Sel == 3'b001)  O1 <= T2;
        else if( O1Sel == 3'b010)  O1 <= T3;
        else if( O1Sel == 3'b011)  O1 <= T4;
        else if( O1Sel == 3'b100)  O1 <= R1;
        else if( O1Sel == 3'b101)  O1 <= R2;
        else if( O1Sel == 3'b110)  O1 <= R3;
        else if( O1Sel == 3'b111)  O1 <= R4;


        if( O2Sel == 3'b000)  O2 <= T1;
        else if( O2Sel == 3'b001)  O2 <= T2;
        else if( O2Sel == 3'b010)  O2 <= T3;
        else if( O2Sel == 3'b011)  O2 <= T4;
        else if( O2Sel == 3'b100)  O2 <= R1;
        else if( O2Sel == 3'b101)  O2 <= R2;
        else if( O2Sel == 3'b110)  O2 <= R3;
        else if( O2Sel == 3'b111)  O2 <= R4;

    end 
endmodule

part2/part2b_tb.v
`timescale 1ns/1ns
`include "part2b.v"


module part2b_tb();

reg clk;
reg [7:0] I;
reg [2:0] O1Sel;
reg [2:0] O2Sel;
reg [1:0] FunSel;
reg [3:0] RSel;
reg [3:0] TSel;
wire [7:0] O1, O2;


part2b uut(
    clk,
    I,
    O1Sel,
    O2Sel,
    FunSel,
    RSel,
    TSel,
    O1,
    O2
);

initial begin
    clk = 0;
    forever #5 clk = ~clk;

initial begin
    
    $dumpfile("part2b_tb.vcd");
    $dumpvars(0, part2b_tb);

    I = 8'b00000000;
    O1Sel = 3'b000;
    O2Sel = 3'b000;
    FunSel = 2'b00;
    RSel = 4'b0100;
    TSel = 4'b0001;
    #10;

    I = 8'b00011000;
    O1Sel = 3'b101;
    O2Sel = 3'b011;
    FunSel = 2'b01;
    RSel = 4'b0100;
    TSel = 4'b0001;
    #10;

    I = 8'b00011000;
    O1Sel = 3'b101;
    O2Sel = 3'b011;
    FunSel = 2'b10;
    RSel = 4'b0100;
    TSel = 4'b0001;
    #10;
    
    I = 8'b00011000;
    O1Sel = 3'b101;
    O2Sel = 3'b011;
    FunSel = 2'b11;
    RSel = 4'b0100;
    TSel = 4'b0001;
    #10;

    I = 8'b01011110;
    O1Sel = 3'b110;
    O2Sel = 3'b011;
    FunSel = 2'b01;
    RSel = 4'b0010;
    TSel = 4'b0010;
    #10;    

    $display("Simulation Completed..");
    $finish;

end

endmodule

part2/part2b_tb.vcd
$date
	Tue Apr 11 17:33:49 2023
$end
$version
	Icarus Verilog
$end
$timescale
	1ns
$end
$scope module part2b_tb $end
$var wire 8 ! O2 [7:0] $end
$var wire 8 " O1 [7:0] $end
$var reg 2 # FunSel [1:0] $end
$var reg 8 $ I [7:0] $end
$var reg 3 % O1Sel [2:0] $end
$var reg 3 & O2Sel [2:0] $end
$var reg 4 ' RSel [3:0] $end
$var reg 4 ( TSel [3:0] $end
$var reg 1 ) clk $end
$scope module uut $end
$var wire 2 * FunSel [1:0] $end
$var wire 8 + I [7:0] $end
$var wire 3 , O1Sel [2:0] $end
$var wire 3 - O2Sel [2:0] $end
$var wire 4 . RSel [3:0] $end
$var wire 4 / TSel [3:0] $end
$var wire 1 ) clk $end
$var reg 8 0 O1 [7:0] $end
$var reg 8 1 O2 [7:0] $end
$var reg 8 2 R1 [7:0] $end
$var reg 8 3 R2 [7:0] $end
$var reg 8 4 R3 [7:0] $end
$var reg 8 5 R4 [7:0] $end
$var reg 8 6 T1 [7:0] $end
$var reg 8 7 T2 [7:0] $end
$var reg 8 8 T3 [7:0] $end
$var reg 8 9 T4 [7:0] $end
$upscope $end
$upscope $end
$enddefinitions $end
#0
$dumpvars
bx 9
bx 8
bx 7
bx 6
bx 5
bx 4
bx 3
bx 2
bx 1
bx 0
b1 /
b100 .
b0 -
b0 ,
b0 +
b0 *
0)
b1 (
b100 '
b0 &
b0 %
b0 $
b0 #
bx "
bx !
$end
#5
b0 9
b0 3
1)
#10
0)
b1 #
b1 *
b11 &
b11 -
b101 %
b101 ,
b11000 $
b11000 +
#15
b11000 !
b11000 1
b11000 "
b11000 0
b11000 9
b11000 3
1)
#20
0)
b10 #
b10 *
#25
b10111 !
b10111 1
b10111 9
b10111 "
b10111 0
b10111 3
1)
#30
0)
b11 #
b11 *
#35
b11000 !
b11000 1
b11000 9
b11000 "
b11000 0
b11000 3
1)
#40
0)
b10 (
b10 /
b10 '
b10 .
b1 #
b1 *
b110 %
b110 ,
b1011110 $
b1011110 +
#45
b1011110 "
b1011110 0
b1011110 8
b1011110 4
1)
