part2/part2c.v

//Address Register File
module part2c_ARF(
    input clk,
    input [7:0] I,
    input [1:0] OutASel,
    input [1:0] OutBSel,
    input [1:0] FunSel,
    input [3:0] RSel,
    output reg [7:0] OutA,
    output reg [7:0] OutB
);

reg [7:0] PC;
reg [7:0] AR;
reg [7:0] SP;
reg [7:0] PCPast;


always @ (posedge clk) begin

    if(FunSel == 2'b00)
    begin
        if(RSel[3] == 1) 
            PC <= 8'b00000000;
        if(RSel[2] == 1) 
            AR <= 8'b00000000;
        if(RSel[1] == 1) 
            SP <= 8'b00000000;
        if(RSel[0] == 1) 
            PCPast <= 8'b00000000;
    end
    else if(FunSel == 2'b01)
    begin
        if(RSel[3] == 1) 
            PC <= I;
        if(RSel[2] == 1) 
            AR <= I;
        if(RSel[1] == 1) 
            SP <= I;
        if(RSel[0] == 1)
            PCPast <= I;
    end
    else if(FunSel == 2'b10)
    begin
        if(RSel[3] == 1) 
            PC <= PC + 1;
        if(RSel[2] == 1) 
            AR <= AR + 1;
        if(RSel[1] == 1) 
            SP <= SP + 1;
        if(RSel[0] == 1)
            PCPast <= PCPast + 1;
    end
    else if(FunSel == 2'b11)
    begin
        if(RSel[3] == 1) 
            PC <= PC - 1;
        if(RSel[2] == 1) 
            AR <= AR - 1;
        if(RSel[1] == 1) 
            SP <= SP - 1;
        if(RSel[0] == 1)
            PCPast <= PCPast - 1;
    end


    if(OutASel == 2'b00) OutA <= AR;
    else if(OutASel == 2'b01) OutA <= SP;
    else if(OutASel == 2'b10) OutA <= PCPast;
    else if(OutASel == 2'b11) OutA <= PC;

    if(OutBSel == 2'b00) OutB <= AR;
    else if(OutBSel == 2'b01) OutB <= SP;
    else if(OutBSel == 2'b10) OutB <= PCPast;
    else if(OutBSel == 2'b11) OutB <= PC;

end

endmodule

part2/part2c_tb.v
`timescale 1ps/1ps
`include "part2c.v"

module part2c_tb();

reg clk;
reg [7:0] I;
reg [1:0] OutASel, OutBSel, FunSel;
reg [3:0] RSel;

wire [7:0] OutA, OutB;

part2c_ARF part2c_ARF(
    clk,
    I,
    OutASel,
    OutBSel,
    FunSel,
    RSel,
    OutA,
    OutB
);

initial begin
    clk = 0;
    forever #5 clk = ~clk;
end

initial begin
    $dumpfile("part2c_tb.vcd");
    $dumpvars(0, part2c_tb);

    I = 8'b00001000;
    FunSel = 2'b00;
    RSel = 4'b1111;
    OutASel = 2'b00;
    OutBSel = 2'b00;
    #15;

    I = 8'b00001000;
    FunSel = 2'b01;
    RSel = 4'b1001;
    OutASel = 2'b10;
    OutBSel = 2'b11;
    #15;

    I = 8'b00011000;
    FunSel = 2'b10;
    RSel = 4'b1001;
    OutASel = 2'b10;
    OutBSel = 2'b11;
    #15;

    I = 8'b00011000;
    FunSel = 2'b11;
    RSel = 4'b1001;
    OutASel = 2'b10;
    OutBSel = 2'b11;
    #15;

    I = 8'b00011000;
    FunSel = 2'b01;
    RSel = 4'b0110;
    OutASel = 2'b00;
    OutBSel = 2'b01;
    #15;

    I = 8'b00011000;
    FunSel = 2'b00;
    RSel = 4'b0110;
    OutASel = 2'b00;
    OutBSel = 2'b01;
    #15;


    $display("Simulation Complete..");
    $finish;
end

endmodule

part2/part2c_tb.vcd
$date
	Tue Apr 11 17:49:21 2023
$end
$version
	Icarus Verilog
$end
$timescale
	1ps
$end
$scope module part2c_tb $end
$var wire 8 ! OutB [7:0] $end
$var wire 8 " OutA [7:0] $end
$var reg 2 # FunSel [1:0] $end
$var reg 8 $ I [7:0] $end
$var reg 2 % OutASel [1:0] $end
$var reg 2 & OutBSel [1:0] $end
$var reg 4 ' RSel [3:0] $end
$var reg 1 ( clk $end
$scope module part2c_ARF $end
$var wire 2 ) FunSel [1:0] $end
$var wire 8 * I [7:0] $end
$var wire 2 + OutASel [1:0] $end
$var wire 2 , OutBSel [1:0] $end
$var wire 4 - RSel [3:0] $end
$var wire 1 ( clk $end
$var reg 8 . AR [7:0] $end
$var reg 8 / OutA [7:0] $end
$var reg 8 0 OutB [7:0] $end
$var reg 8 1 PC [7:0] $end
$var reg 8 2 PCPast [7:0] $end
$var reg 8 3 SP [7:0] $end
$upscope $end
$upscope $end
$enddefinitions $end
#0
$dumpvars
bx 3
bx 2
bx 1
bx 0
bx /
bx .
b1111 -
b0 ,
b0 +
b1000 *
b0 )
0(
b1111 '
b0 &
b0 %
b1000 $
b0 #
bx "
bx !
$end
#5
b0 2
b0 3
b0 .
b0 1
1(
#10
0(
#15
b0 !
b0 0
b0 "
b0 /
b1000 2
b1000 1
1(
b11 &
b11 ,
b10 %
b10 +
b1001 '
b1001 -
b1 #
b1 )
#20
0(
#25
b1000 !
b1000 0
b1000 "
b1000 /
1(
#30
0(
b10 #
b10 )
b11000 $
b11000 *
#35
b1001 2
b1001 1
1(
#40
0(
#45
b1001 !
b1001 0
b1001 "
b1001 /
b1000 2
b1000 1
1(
b11 #
b11 )
#50
0(
#55
b1000 !
b1000 0
b1000 "
b1000 /
b111 2
b111 1
1(
#60
0(
b1 &
b1 ,
b0 %
b0 +
b110 '
b110 -
b1 #
b1 )
#65
b0 !
b0 0
b0 "
b0 /
b11000 3
b11000 .
1(
#70
0(
#75
b11000 !
b11000 0
b11000 "
b11000 /
b0 3
b0 .
1(
b0 #
b0 )
#80
0(
#85
b0 !
b0 0
b0 "
b0 /
1(
