part2/part2a.v
// a 16-bit IR register that can store 16 bit binary data. However, the input of this register file is only 8 bits. Therefore, using the 8-bit input bus, you can load either the lower (bits 7-0) or higher (bits 15-8) half. This decision is made by the LH signal.


module part2a(input[7:0] I, input [1:0] FunSel, input LH, input enable, output reg [15:0] data_out);

    always @(FunSel or I or enable or LH)
    begin
        if (enable == 0)
            data_out <= data_out;
        else
            case (FunSel)
                2'b00: data_out <= 16'b000000000000000;
                2'b01: 
                case (LH)
                    0: data_out[7:0] <= I;
                    1: data_out[15:8] <= I;
                endcase
                2'b10: data_out <= data_out - 1;
                2'b11: data_out <= data_out + 1;
            endcase
    end

endmodule

part2/part2a_tb.v
`timescale 1ns/1ns
`include "part2a.v"


module part2a_tb();

reg [7:0] I;
reg [1:0] FunSel;
reg LH;
reg enable;
wire [15:0] data_out;

part2a part2a_inst (I, FunSel, LH, enable, data_out);

initial begin

    $dumpfile("part2a_tb.vcd");
    $dumpvars(0, part2a_tb);

    enable = 0;
    FunSel = 2'b0;
    I = 8'b0;
    LH = 0;
    #10;

    enable = 0;
    FunSel = 2'b01;
    I = 8'b10101010;
    LH = 1;
    #10;

    enable = 1;
    #10

    enable = 0;
    #10;

    enable = 1;
    FunSel = 2'b01;
    I = 8'b00000101;
    LH = 0;
    #10;

    enable = 1;
    FunSel = 2'b10;
    I = 8'b00000101;
    LH = 0;
    #10;

    enable = 1;
    FunSel = 2'b11;
    I = 8'b00000111;
    LH = 0;
    #10;

    enable = 0;
    FunSel = 2'b0;
    I = 8'b0;
    LH = 0;
    #10;

    $finish;
end

endmodule

part2/part2a_tb.vcd
$date
	Tue Apr  4 17:13:58 2023
$end
$version
	Icarus Verilog
$end
$timescale
	1ns
$end
$scope module part2a_tb $end
$var wire 16 ! data_out [15:0] $end
$var reg 2 " FunSel [1:0] $end
$var reg 8 # I [7:0] $end
$var reg 1 $ LH $end
$var reg 1 % enable $end
$scope module part2a_inst $end
$var wire 2 & FunSel [1:0] $end
$var wire 8 ' I [7:0] $end
$var wire 1 $ LH $end
$var wire 1 % enable $end
$var reg 16 ( data_out [15:0] $end
$upscope $end
$upscope $end
$enddefinitions $end
#0
$dumpvars
bx (
b0 '
b0 &
0%
0$
b0 #
b0 "
bx !
$end
#10
1$
b10101010 #
b10101010 '
b1 "
b1 &
#20
b10101010xxxxxxxx !
b10101010xxxxxxxx (
1%
#30
0%
#40
b1010101000000101 !
b1010101000000101 (
0$
b101 #
b101 '
1%
#50
b1010101000000100 !
b1010101000000100 (
b10 "
b10 &
#60
b1010101000000101 !
b1010101000000101 (
b111 #
b111 '
b11 "
b11 &
#70
b0 #
b0 '
b0 "
b0 &
0%
