part2/part2c.v

//Address Register File
module part2c_ARF(
    input clk,
    input [7:0] I,
    input [1:0] OutASel,
    input [1:0] OutBSel,
    input [1:0] FunSel,
    input [2:0] RSel,
    output reg [7:0] OutA,
    output reg [7:0] OutB
);

reg [7:0] PC;
reg [7:0] AR;
reg [7:0] SP;
reg [7:0] PCPast;


always @ (posedge clk) begin

    PCPast <= PC;

    case (FunSel)
        2'b00:
        begin
            if(RSel[0] == 1) 
                PC <= 8'b00000000;
            if(RSel[1] == 1) 
                AR <= 8'b00000000;
            if(RSel[2] == 1) 
                SP <= 8'b00000000;
        end
        2'b01:
        begin
            if(RSel[0] == 1) 
                PC <= I;
            if(RSel[1] == 1) 
                AR <= I;
            if(RSel[2] == 1) 
                SP <= I;
        end
        2'b10:
        begin
            if(RSel[2] == 1) 
                PC <= PC + 1;
            if(RSel[1] == 1) 
                AR <= AR + 1;
            if(RSel[0] == 1) 
                SP <= SP + 1;
        end
        2'b11:
        begin
            if(RSel[2] == 1) 
                PC <= PC - 1;
            if(RSel[1] == 1) 
                AR <= AR - 1;
            if(RSel[0] == 1) 
                SP <= SP - 1;
        end
    endcase


    case (OutASel)
        2'b00: OutA <= AR;
        2'b01: OutA <= SP;
        2'b10: OutA <= PCPast;
        2'b11: OutA <= PC;
    endcase

    case (OutBSel)
        2'b00: OutB <= AR;
        2'b01: OutB <= SP;
        2'b10: OutB <= PCPast;
        2'b11: OutB <= PC;
    endcase

end

endmodule

part2/part2c_tb.v
`timescale 1ps/1ps
`include "part2c.v"

module part2c_tb();

reg clk;
reg [7:0] I;
reg [1:0] OutASel, OutBSel, FunSel;
reg [2:0] RSel;

wire [7:0] OutA, OutB;

part2c_ARF part2c_ARF(
    clk,
    I,
    OutASel,
    OutBSel,
    FunSel,
    RSel,
    OutA,
    OutB
);

initial begin
    clk = 0;
    forever #5 clk = ~clk;
end

initial begin
    $dumpfile("part2c_tb.vcd");
    $dumpvars(0, part2c_tb);

    #50

    I = 8'b00000100;
    OutASel = 2'b00;
    OutBSel = 2'b11;
    FunSel = 2'b01;
    RSel = 3'b011;
    #50

    I = 8'b00000110;
    OutASel = 2'b10;
    OutBSel = 2'b11;
    FunSel = 2'b01;
    RSel = 3'b011;
    #50

    I = 8'b00000000;
    OutASel = 2'b10;
    OutBSel = 2'b11;
    FunSel = 2'b00;
    RSel = 3'b011;
    #50

    $display("Simulation Complete..");
    $finish;
end

endmodule

part2/part2c_tb.vcd
$date
	Sun Apr  9 01:37:39 2023
$end
$version
	Icarus Verilog
$end
$timescale
	1ps
$end
$scope module part2c_tb $end
$var wire 8 ! OutB [7:0] $end
$var wire 8 " OutA [7:0] $end
$var reg 2 # FunSel [1:0] $end
$var reg 8 $ I [7:0] $end
$var reg 2 % OutASel [1:0] $end
$var reg 2 & OutBSel [1:0] $end
$var reg 3 ' RSel [2:0] $end
$var reg 1 ( clk $end
$scope module part2c_ARF $end
$var wire 2 ) FunSel [1:0] $end
$var wire 8 * I [7:0] $end
$var wire 2 + OutASel [1:0] $end
$var wire 2 , OutBSel [1:0] $end
$var wire 3 - RSel [2:0] $end
$var wire 1 ( clk $end
$var reg 8 . AR [7:0] $end
$var reg 8 / OutA [7:0] $end
$var reg 8 0 OutB [7:0] $end
$var reg 8 1 PC [7:0] $end
$var reg 8 2 PCPast [7:0] $end
$var reg 8 3 SP [7:0] $end
$upscope $end
$upscope $end
$enddefinitions $end
#0
$dumpvars
bx 3
bx 2
bx 1
bx 0
bx /
bx .
bx -
bx ,
bx +
bx *
bx )
0(
bx '
bx &
bx %
bx $
bx #
bx "
bx !
$end
#5
1(
#10
0(
#15
1(
#20
0(
#25
1(
#30
0(
#35
1(
#40
0(
#45
1(
#50
0(
b11 '
b11 -
b1 #
b1 )
b11 &
b11 ,
b0 %
b0 +
b100 $
b100 *
#55
b100 .
b100 1
1(
#60
0(
#65
b100 !
b100 0
b100 "
b100 /
b100 2
1(
#70
0(
#75
1(
#80
0(
#85
1(
#90
0(
#95
1(
#100
0(
b10 %
b10 +
b110 $
b110 *
#105
b110 .
b110 1
1(
#110
0(
#115
b110 !
b110 0
b110 2
1(
#120
0(
#125
b110 "
b110 /
1(
#130
0(
#135
1(
#140
0(
#145
1(
#150
0(
b0 #
b0 )
b0 $
b0 *
#155
b0 .
b0 1
1(
#160
0(
#165
b0 !
b0 0
b0 2
1(
#170
0(
#175
b0 "
b0 /
1(
