part3/ALU.v
`timescale 1ns/1ps
//////////////////////////////////////////////////////////////////////////////////
// Company: 
// Engineer: 
// 
// Create Date: 05.04.2023 01:29:48
// Design Name: 
// Module Name: ALU
// Project Name: 
// Target Devices: 
// Tool Versions: 
// Description: 
// 
// Dependencies: 
// 
// Revision:
// Revision 0.01 - File Created
// Additional Comments:
// 
//////////////////////////////////////////////////////////////////////////////////


module ALU (
    input [7:0] A,
    input [7:0] B,
    input [3:0] FunSel,
    input clk,
    output reg [7:0] OutALU,
    output reg [3:0] Flags // ZCNO
);

    reg [8:0] temp_result;
    reg [7:0] B_neg;

    always @(posedge clk) begin
        B_neg = (~B) + 8'b00000001; // 2's complement of B

        case (FunSel)
          4'b0000: begin // A
                OutALU <= A;
                Flags[0] <= (A == 8'b0); // Z flag
                Flags[2] <= A[7]; // N flag
            end
            4'b0001: begin // B
                OutALU <= B;
                Flags[0] <= (B == 8'b0); // Z flag
                Flags[2] <= B[7]; // N flag
            end
            4'b0010: begin // NOT A
                OutALU <= ~A;
                Flags[0] <= (OutALU == 8'b0); // Z flag
                Flags[2] <= OutALU[7]; // N flag
            end
            4'b0011: begin // NOT B
                OutALU <= ~B;
                Flags[0] <= (OutALU == 8'b0); // Z flag
                Flags[2] <= OutALU[7]; // N flag
            end
            4'b0100: begin // Addition
                temp_result = A + B;
                OutALU <= temp_result[7:0];
                Flags[0] <= (temp_result == 9'b0); // Z flag
                Flags[1] <= temp_result[8]; // C flag
                Flags[2] <= temp_result[7]; // N flag
                Flags[3] <= (A[7] & B[7] & ~temp_result[7]) | (~(A[7] | B[7]) & temp_result[7]); // O flag
            end
            4'b0101: begin // Subtraction
                temp_result = A + B_neg; // Perform subtraction using 2's complement addition
                OutALU <= temp_result[7:0];
                Flags[0] <= (temp_result == 9'b0); // Z flag
                Flags[1] <= (A[7] & ~B[7]) & ~temp_result[7]; // C flag
                Flags[2] <= temp_result[7]; // N flag
                Flags[3] <= Flags[3] <= (A[7] & ~B[7] & ~temp_result[7]) | (~A[7] & B[7] & temp_result[7]); // O flag
            end
            4'b0110: begin // Compare A, B
                if (A == B) begin
                    OutALU <= 8'b0;
                    Flags <= 4'b0001; // Z flag
                end else if (A[7] == 0 && B[7] == 1) begin
                    OutALU <= A;
                    Flags <= 4'b0000; 
                end else if (A[7] == 1 && B[7] == 0) begin
                    OutALU <= 8'b0;
                    Flags <= 4'b0100; // N flag
                end else if (A > B) begin
                    OutALU <= A;
                    Flags <= 4'b0000; 
                end else begin
                    OutALU <= 8'b0;
                    Flags <= 4'b0100; // N flag
                end
            end
            4'b0111: begin // A AND B
                OutALU <= A & B;
                Flags[0] <= (OutALU == 8'b0); // Z flag
                Flags[2] <= OutALU[7]; // N flag
            end
            4'b1000: begin // A OR B
                OutALU <= A | B;
                Flags[0] <= (OutALU == 8'b0); // Z flag
                Flags[2] <= OutALU[7]; // N flag
            end
            4'b1001: begin // A NAND B
                OutALU <= ~(A & B);
                Flags[0] <= (OutALU == 8'b0); // Z flag
                Flags[2] <= OutALU[7]; // N flag
            end
            4'b1010: begin // A XOR B
                OutALU <= A ^ B;
                Flags[0] <= (OutALU == 8'b0); // Z flag
                Flags[2] <= OutALU[7]; // N flag
            end
             4'b1011: begin // LSL A
                OutALU <= {A[6:0], 1'b0};
                Flags[0] <= (OutALU == 8'b0); // Z flag
                Flags[1] <= A[7]; // C flag
                Flags[2] <= OutALU[7]; // N flag
            end
            4'b1100: begin // LSR A
                OutALU <= {1'b0, A[7:1]};
                Flags[0] <= (OutALU == 8'b0); // Z flag
                Flags[1] <= A[0]; // C flag
                Flags[2] <= OutALU[7]; // N flag
            end
           4'b1101: begin // ASL A
                OutALU <= {A[6:0], 1'b0};
                Flags[0] <= (OutALU == 8'b0); // Z flag
                Flags[2] <= OutALU[7]; // N flag
                Flags[3] <= (A[7] == 1'b1) ? 1'b1 : 1'b0; // O flag
            end
            4'b1110: begin // ASR A
                OutALU <= {A[7], A[7:1]};
                Flags[0] <= (OutALU == 8'b0); // Z flag
            end
           4'b1111: begin // CSR A
            OutALU <= {A[0], A[7:1]};
            Flags[0] <= (OutALU == 8'b0); // Z flag
            Flags[1] <= A[0]; // C flag
            Flags[2] <= OutALU[7]; // N flag
        end
        endcase
    end
endmodule

part3/ALU_tb.v
`timescale 1ns / 1ps
`include "ALU.v"
//////////////////////////////////////////////////////////////////////////////////
// Company: 
// Engineer: 
// 
// Create Date: 05.04.2023 02:33:06
// Design Name: 
// Module Name: alu_tb
// Project Name: 
// Target Devices: 
// Tool Versions: 
// Description: 
// 
// Dependencies: 
// 
// Revision:
// Revision 0.01 - File Created
// Additional Comments:
// 
//////////////////////////////////////////////////////////////////////////////////


module ALU_tb;

    reg [7:0] A_tb;
    reg [7:0] B_tb;
    reg [3:0] FunSel_tb;
    reg clk_tb;

    wire [7:0] OutALU_tb;
    wire [3:0] Flags_tb;

    ALU ALU_inst (
        .A(A_tb),
        .B(B_tb),
        .FunSel(FunSel_tb),
        .clk(clk_tb),
        .OutALU(OutALU_tb),
        .Flags(Flags_tb)
    );

    always #5 clk_tb = ~clk_tb;

    initial begin

        $dumpfile("ALU_tb.vcd");
        $dumpvars(0, ALU_tb);

        A_tb = 8'b00000001;
        B_tb = 8'b00000000;
        FunSel_tb = 4'b0000;
        clk_tb = 1'b0;

        #10;

        // Test ADD operation
        A_tb = 8'b00110011;
        B_tb = 8'b00001111;
        FunSel_tb = 4'b0100;
        #10;
        $display("ADD operation result: %b", OutALU_tb);
        $display("ADD operation flags: %b", Flags_tb);

        // Test SUB operation
        A_tb = 8'b00000111;
        B_tb = 8'b11111010;
        FunSel_tb = 4'b0101;
        #10;
        $display("SUB operation result: %b", OutALU_tb);
        $display("SUB operation flags: %b", Flags_tb);
        
        // Test Compare operation
        A_tb = 8'b01000000;
        B_tb = 8'b00111000;
        FunSel_tb = 4'b0110;
        #10;
        $display("Compare operation result: %b", OutALU_tb);
        $display("Compare operation flags: %b", Flags_tb);
        // Test AND operation
        A_tb = 8'b10101010;
        B_tb = 8'b11110000;
        FunSel_tb = 4'b0111;
        #10;
        $display("AND operation result: %b", OutALU_tb);
        $display("AND operation flags: %b", Flags_tb);

        // Test OR operation
        A_tb = 8'b10101010;
        B_tb = 8'b11110000;
        FunSel_tb = 4'b1000;
        #10;
        $display("OR operation result: %b", OutALU_tb);
        $display("OR operation flags: %b", Flags_tb);

        // Test XOR operation
        A_tb = 8'b10101010;
        B_tb = 8'b11110000;
        FunSel_tb = 4'b1010;
        #10;
        $display("XOR operation result: %b", OutALU_tb);
        $display("XOR operation flags: %b", Flags_tb);

        // Test LSL operation
        A_tb = 8'b00110011;
        B_tb = 8'b00000000;
        FunSel_tb = 4'b1011;
        #10;
        $display("LSL operation result: %b", OutALU_tb);
        $display("LSL operation flags: %b", Flags_tb);

        // Test LSR operation
        A_tb = 8'b00110011;
        B_tb = 8'b00000000;
        FunSel_tb = 4'b1100;
        #10;
        $display("LSR operation result: %b", OutALU_tb);
        $display("LSR operation flags: %b", Flags_tb);

        // Test ASL
        A_tb = 8'b10000000;
        B_tb = 8'b00000000;
        FunSel_tb = 4'b1101;
        #10;
        $display("ASL operation result: %b", OutALU_tb);
        $display("ASL operation flags: %b", Flags_tb);

        // Test ASR operation
        A_tb = 8'b00110011;
        B_tb = 8'b00000000;
        FunSel_tb = 4'b1110;
        #10;
        $display("ASR operation result: %b", OutALU_tb);
        $display("ASR operation flags: %b", Flags_tb);

        // Test CSR operation
        A_tb = 8'b10000000;
        B_tb = 8'b00000000;
        FunSel_tb = 4'b1111;
        #10;
        $display("CSR operation result: %b", OutALU_tb);
        $display("CSR operation flags: %b", Flags_tb);

        // Finish simulation
        $finish;
        #10;
end
endmodule

part3/ALU_tb.vcd
$date
	Wed Apr  5 16:47:12 2023
$end
$version
	Icarus Verilog
$end
$timescale
	1ps
$end
$scope module ALU_tb $end
$var wire 8 ! OutALU_tb [7:0] $end
$var wire 4 " Flags_tb [3:0] $end
$var reg 8 # A_tb [7:0] $end
$var reg 8 $ B_tb [7:0] $end
$var reg 4 % FunSel_tb [3:0] $end
$var reg 1 & clk_tb $end
$scope module ALU_inst $end
$var wire 8 ' A [7:0] $end
$var wire 8 ( B [7:0] $end
$var wire 4 ) FunSel [3:0] $end
$var wire 1 & clk $end
$var reg 8 * B_neg [7:0] $end
$var reg 4 + Flags [3:0] $end
$var reg 8 , OutALU [7:0] $end
$var reg 9 - temp_result [8:0] $end
$upscope $end
$upscope $end
$enddefinitions $end
#0
$dumpvars
bx -
bx ,
bx +
bx *
b0 )
b0 (
b1 '
0&
b0 %
b0 $
b1 #
bx "
bx !
$end
#5000
bx0x0 "
bx0x0 +
b1 !
b1 ,
b0 *
1&
#10000
0&
b100 %
b100 )
b1111 $
b1111 (
b110011 #
b110011 '
#15000
b0 "
b0 +
b1000010 !
b1000010 ,
b1000010 -
b11110001 *
1&
#20000
0&
b101 %
b101 )
b11111010 $
b11111010 (
b111 #
b111 '
#25000
b1010 "
b1010 +
b1101 !
b1101 ,
b1101 -
b110 *
1&
#30000
0&
b110 %
b110 )
b111000 $
b111000 (
b1000000 #
b1000000 '
#35000
b0 "
b0 +
b1000000 !
b1000000 ,
b11001000 *
1&
#40000
0&
b111 %
b111 )
b11110000 $
b11110000 (
b10101010 #
b10101010 '
#45000
b10100000 !
b10100000 ,
b10000 *
1&
#50000
0&
b1000 %
b1000 )
#55000
b100 "
b100 +
b11111010 !
b11111010 ,
1&
#60000
0&
b1010 %
b1010 )
#65000
b1011010 !
b1011010 ,
1&
#70000
0&
b1011 %
b1011 )
b0 $
b0 (
b110011 #
b110011 '
#75000
b0 "
b0 +
b1100110 !
b1100110 ,
b0 *
1&
#80000
0&
b1100 %
b1100 )
#85000
b10 "
b10 +
b11001 !
b11001 ,
1&
#90000
0&
b1101 %
b1101 )
b10000000 #
b10000000 '
#95000
b1010 "
b1010 +
b0 !
b0 ,
1&
#100000
0&
b1110 %
b1110 )
b110011 #
b110011 '
#105000
b1011 "
b1011 +
b11001 !
b11001 ,
1&
#110000
0&
b1111 %
b1111 )
b10000000 #
b10000000 '
#115000
b1000 "
b1000 +
b1000000 !
b1000000 ,
1&
