part1/part1.v

module part1 #(parameter n = 4) (input clk, input [1:0] FunSel, input [n-1:0] data_in, input enable, output reg [n-1:0] data_out);


    wire [n-1:0] zero = 0;
    always @(posedge clk)
    begin
        if (enable == 0)
            data_out <= data_out;
        else
            case (FunSel)
                2'b00: data_out <= zero;
                2'b01: data_out <= data_in;
                2'b10: data_out <= data_out - 1;
                2'b11: data_out <= data_out + 1;
            endcase
    end

endmodule

part1/part1_tb.v
`timescale 1ns/1ns
`include "part1.v"

module part1_tb();

reg [1:0] FunSel;
reg [3:0] data_in;
reg enable;
reg clk;
wire [3:0] data_out;

part1 #(4) part1_inst (clk, FunSel, data_in, enable, data_out);

always begin

    clk = 0;
    forever #5 clk = ~clk;
end

initial begin

    $dumpfile("part1_tb.vcd");
    $dumpvars(0, part1_tb);

    FunSel = 2'b00;
    data_in = 4'b0010;
    enable = 0;
    #10;

    FunSel = 2'b00;
    data_in = 4'b0010;
    enable = 1;
    #10;

    FunSel = 2'b01;
    data_in = 4'b0010;
    enable = 1;
    #10;

    FunSel = 2'b10;
    data_in = 4'b0010;
    enable = 1;
    #10;

    FunSel = 2'b11;
    data_in = 4'b0110;
    enable = 1;
    #10;

    FunSel = 2'b01;
    data_in = 4'b0110;
    enable = 0;
    #10;

    FunSel = 2'b00;
    data_in = 4'b0010;
    enable = 1;
    #10;
    
    $finish;

end

endmodule

part1/part1_tb.vcd
$date
	Tue Apr 11 00:14:36 2023
$end
$version
	Icarus Verilog
$end
$timescale
	1ns
$end
$scope module part1_tb $end
$var wire 4 ! data_out [3:0] $end
$var reg 2 " FunSel [1:0] $end
$var reg 1 # clk $end
$var reg 4 $ data_in [3:0] $end
$var reg 1 % enable $end
$scope module part1_inst $end
$var wire 2 & FunSel [1:0] $end
$var wire 1 # clk $end
$var wire 4 ' data_in [3:0] $end
$var wire 1 % enable $end
$var wire 4 ( zero [3:0] $end
$var reg 4 ) data_out [3:0] $end
$upscope $end
$upscope $end
$enddefinitions $end
#0
$dumpvars
bx )
b0 (
b10 '
b0 &
0%
b10 $
0#
b0 "
bx !
$end
#5
1#
#10
0#
1%
#15
b0 !
b0 )
1#
#20
0#
b1 "
b1 &
#25
b10 !
b10 )
1#
#30
0#
b10 "
b10 &
#35
b1 !
b1 )
1#
#40
0#
b110 $
b110 '
b11 "
b11 &
#45
b10 !
b10 )
1#
#50
0#
0%
b1 "
b1 &
#55
1#
#60
0#
1%
b10 $
b10 '
b0 "
b0 &
#65
b0 !
b0 )
1#
